setup.py
digPriceExtractor/__init__.py
digPriceExtractor/price_extractor.py
digPriceExtractor.egg-info/PKG-INFO
digPriceExtractor.egg-info/SOURCES.txt
digPriceExtractor.egg-info/dependency_links.txt
digPriceExtractor.egg-info/requires.txt
digPriceExtractor.egg-info/top_level.txt
digPriceExtractor/digpe/__init__.py
digPriceExtractor/digpe/extractor.py
digPriceExtractor/digpe/normalizer.py
digPriceExtractor/digpe/preprocessor.py
digPriceExtractor/digpe/unit/__init__.py
digPriceExtractor/digpe/unit/price_units.py
digPriceExtractor/digpe/unit/time_units.py
test/__init__.py
test/test_price_extractor.py