Metadata-Version: 1.1
Name: digPriceExtractor
Version: 0.3.2
Summary: digPriceExtractor
Home-page: https://github.com/usc-isi-i2/dig-price-extractor
Author: Lingzhe Teng
Author-email: zwein27@gmail.com
License: UNKNOWN
Download-URL: https://github.com/usc-isi-i2/dig-price-extractor
Keywords: price,extractor
Platform: UNKNOWN
